onlinerake/__init__.py
onlinerake/online_raking_mwu.py
onlinerake/online_raking_sgd.py
onlinerake/py.typed
onlinerake/targets.py
onlinerake-1.0.0.dist-info/WHEEL
onlinerake-1.0.0.dist-info/METADATA
onlinerake-1.0.0.dist-info/RECORD
