Metadata-Version: 2.3
Name: onlinerake
Version: 1.0.0
Summary: Streaming survey raking via SGD and MWU
Author: Gaurav Sood
Author-email: Gaurav Sood <gsood07@gmail.com>
License: MIT
Requires-Dist: numpy>=1.21
Requires-Dist: pandas>=1.3
Requires-Dist: sphinx>=7.0 ; extra == 'docs'
Requires-Dist: furo>=2024.1.29 ; extra == 'docs'
Requires-Dist: sphinx-autodoc-typehints>=1.25 ; extra == 'docs'
Requires-Dist: sphinx-copybutton>=0.5 ; extra == 'docs'
Requires-Dist: myst-parser>=2.0 ; extra == 'docs'
Requires-Dist: nbsphinx>=0.8.0 ; extra == 'docs'
Requires-Dist: jupyter>=1.0.0 ; extra == 'docs'
Requires-Dist: matplotlib>=3.5.0 ; extra == 'docs'
Requires-Dist: seaborn>=0.11.0 ; extra == 'docs'
Requires-Dist: plotly>=5.0.0 ; extra == 'docs'
Requires-Dist: ipywidgets>=7.6.0 ; extra == 'docs'
Requires-Python: >=3.11
Provides-Extra: docs
